storm_tuner/__init__.py
storm_tuner/tuner.py
storm_tuner-0.0.9.dist-info/LICENSE
storm_tuner-0.0.9.dist-info/METADATA
storm_tuner-0.0.9.dist-info/WHEEL
storm_tuner-0.0.9.dist-info/top_level.txt
storm_tuner-0.0.9.dist-info/RECORD
