Metadata-Version: 2.1
Name: storm-tuner
Version: 0.0.9
Summary: neural network hyperparameter tuner
Home-page: https://github.com/ben-arnao/StoRM
Author: Ben Arnao
Author-email: arnaoben@gmail.com
License: UNKNOWN
Project-URL: Bug Tracker, https://github.com/ben-arnao/StoRM/issues
Platform: UNKNOWN
Classifier: Programming Language :: Python :: 3
Classifier: License :: OSI Approved :: MIT License
Classifier: Operating System :: OS Independent
Requires-Python: >=3.6
